{
    "created_at": "Tue Sep 25 18:39:27 +0000 2018",
    "id": 1044657651731386370,
    "id_str": "1044657651731386370",
    "text": "@TwitterDev Hey. I applied for my developer account last Friday, because I am taking a class on quantitative text a… https://t.co/O1kTd8kws1",
    "source": "<a href=\"http://twitter.com\" rel=\"nofollow\">Twitter Web Client</a>",
    "truncated": true,
    "in_reply_to_status_id": null,
    "in_reply_to_status_id_str": null,
    "in_reply_to_user_id": 2244994945,
    "in_reply_to_user_id_str": "2244994945",
    "in_reply_to_screen_name": "TwitterDev",
    "user": {
        "id": 1897757239,
        "id_str": "1897757239",
        "name": "LIU Han",
        "screen_name": "schweinliu",
        "location": "New York, USA",
        "url": null,
        "description": "😇😇😇😇😇😇",
        "translator_type": "none",
        "protected": false,
        "verified": false,
        "followers_count": 6,
        "friends_count": 65,
        "listed_count": 0,
        "favourites_count": 2,
        "statuses_count": 13,
        "created_at": "Mon Sep 23 16:14:50 +0000 2013",
        "utc_offset": null,
        "time_zone": null,
        "geo_enabled": true,
        "lang": "en",
        "contributors_enabled": false,
        "is_translator": false,
        "profile_background_color": "C0DEED",
        "profile_background_image_url": "http://abs.twimg.com/images/themes/theme1/bg.png",
        "profile_background_image_url_https": "https://abs.twimg.com/images/themes/theme1/bg.png",
        "profile_background_tile": false,
        "profile_link_color": "1DA1F2",
        "profile_sidebar_border_color": "C0DEED",
        "profile_sidebar_fill_color": "DDEEF6",
        "profile_text_color": "333333",
        "profile_use_background_image": true,
        "profile_image_url": "http://pbs.twimg.com/profile_images/1044658612088569856/ZBS73GBc_normal.jpg",
        "profile_image_url_https": "https://pbs.twimg.com/profile_images/1044658612088569856/ZBS73GBc_normal.jpg",
        "default_profile": true,
        "default_profile_image": false,
        "following": null,
        "follow_request_sent": null,
        "notifications": null
    },
    "geo": null,
    "coordinates": null,
    "place": null,
    "contributors": null,
    "is_quote_status": false,
    "extended_tweet": {
        "full_text": "@TwitterDev Hey. I applied for my developer account last Friday, because I am taking a class on quantitative text analysis. We are going to use the developer account this Friday but my application is still under review. I am just wondering what is going on with my application!",
        "display_text_range": [
            0,
            277
        ],
        "entities": {
            "hashtags": [],
            "urls": [],
            "user_mentions": [
                {
                    "screen_name": "TwitterDev",
                    "name": "Twitter Dev",
                    "id": 2244994945,
                    "id_str": "2244994945",
                    "indices": [
                        0,
                        11
                    ]
                }
            ],
            "symbols": []
        }
    },
    "quote_count": 0,
    "reply_count": 0,
    "retweet_count": 0,
    "favorite_count": 0,
    "entities": {
        "hashtags": [],
        "urls": [
            {
                "url": "https://t.co/O1kTd8kws1",
                "expanded_url": "https://twitter.com/i/web/status/1044657651731386370",
                "display_url": "twitter.com/i/web/status/1…",
                "indices": [
                    117,
                    140
                ]
            }
        ],
        "user_mentions": [
            {
                "screen_name": "TwitterDev",
                "name": "Twitter Dev",
                "id": 2244994945,
                "id_str": "2244994945",
                "indices": [
                    0,
                    11
                ]
            }
        ],
        "symbols": []
    },
    "favorited": false,
    "retweeted": false,
    "filter_level": "low",
    "lang": "en",
    "matching_rules": [
        {
            "tag": null
        }
    ]
}